core_api_tools/__init__.py
core_api_tools/admin.py
core_api_tools/auth.py
core_api_tools/tests.py
core_api_tools-0.0.6.dist-info/METADATA
core_api_tools-0.0.6.dist-info/WHEEL
core_api_tools-0.0.6.dist-info/top_level.txt
core_api_tools-0.0.6.dist-info/RECORD
